LICENSE
MANIFEST.in
README.md
package.json
setup.py
denis_dash_components/DenisDashComponents.py
denis_dash_components/HtmlInput.py
denis_dash_components/MultiRangeInput.py
denis_dash_components/__init__.py
denis_dash_components/_imports_.py
denis_dash_components/denis_dash_components.min.js
denis_dash_components/denis_dash_components.min.js.map
denis_dash_components/metadata.json
denis_dash_components/package-info.json
denis_dash_components.egg-info/PKG-INFO
denis_dash_components.egg-info/SOURCES.txt
denis_dash_components.egg-info/dependency_links.txt
denis_dash_components.egg-info/top_level.txt