Metadata-Version: 1.1
Name: denis-dash-components
Version: 0.0.1
Summary: A few components, not yet available
Home-page: UNKNOWN
Author: Denis Mijatovic <denis.mijatovic@gmx.at>
Author-email: UNKNOWN
License: MIT
Platform: UNKNOWN
Classifier: Framework :: Dash
